{
    "captions": {
        "1": {
            "caption": "Figure 1.  We created a virtual environment for designers, in which they can generate and arrange an arbitrary number of devices that execute real-\nworld  web  applications  (A).  This  allows  simulation  of  existing  interactive  spaces  and  multi-device  systems  (B,  C)  [71],  as  well  as  sketching  of  new \ninteractions with diverse tracking systems or futuristic devices, e.g., a cylindrical touch screen (D). \n",
            "bbox": [
                53.64208,
                479.16877,
                566.43985,
                505.07126999999997
            ],
            "page": "1"
        },
        "2": {
            "caption": "Figure 2. Our experimental design tool uses \ufb01nger and hand tracking to \nlet users naturally interact with devices and objects in the VE. \n",
            "bbox": [
                321.094,
                596.11202,
                566.1555599999999,
                613.04827
            ],
            "page": "4"
        },
        "3": {
            "caption": "Figure 3.  Simulations of existing systems in VR (right) and the original \nsystem (left).  1) Window Manager by Klokmose et al.  [49] for 75 LCD \ntiles.  2)  VisTiles  by  Langner  et  al.  [51].  3)  Peephole  navigation  with \nHuddleLamp by R\u00e4dle et al. [73]. 4) Edge Bubbles by R\u00e4dle et al. [74]. \n",
            "bbox": [
                53.61020000000002,
                431.55676,
                298.99056,
                466.48927
            ],
            "page": "5"
        },
        "4": {
            "caption": "Figure 4.  VR-based design tools can enable designers to experience fu-\nturistic  touchscreen  devices,  e.g.,  Google  Maps  on  a  cylindrical  touch-\nscreen or drawing on a spherical display. \n",
            "bbox": [
                53.929,
                574.1417700000001,
                298.32108,
                600.04427
            ],
            "page": "6"
        },
        "5": {
            "caption": "Figure 5.  In design mode (A), users can manipulate device properties and resize them.  In use mode (B), users can draw on devices and interact with \nreal-world applications using (multi-)touch. \n",
            "bbox": [
                53.929,
                634.06502,
                566.15293,
                651.00127
            ],
            "page": "7"
        },
        "6": {
            "caption": "Figure 6. P6 tiptoes (left) and P9 jumps (right) to reach overhead targets. \n",
            "bbox": [
                321.094,
                630.49627,
                567.5503099999997,
                638.46627
            ],
            "page": "8"
        },
        "7": {
            "caption": "Figure  7.  P1  throwing  a  ball  at  the  targets  on  the  display  (left).  P6 \npicking up a tablet she dropped (right). \n",
            "bbox": [
                53.929,
                201.12502,
                298.9905599999999,
                218.06127
            ],
            "page": "9"
        }
    },
    "crops": {
        "1": {
            "crop_coord": [
                144.80278027777777,
                529.6584319444446,
                1572.052798888889,
                789.0944502777778
            ],
            "bbox": [
                53.9290009,
                509.7259979,
                564.1390076,
                599.5229645
            ],
            "page": "1"
        },
        "2": {
            "crop_coord": [
                886.9277613888887,
                168.21849416666672,
                1572.1499886111108,
                489.1583252777777
            ],
            "bbox": [
                321.0939941,
                617.7030029,
                564.1739958999999,
                729.6413421
            ],
            "page": "4"
        },
        "3": {
            "crop_coord": [
                144.80278027777777,
                168.23036194444455,
                829.9975416666667,
                896.2694294444445
            ],
            "bbox": [
                53.9290009,
                471.1430054,
                296.999115,
                729.6370697
            ],
            "page": "5"
        },
        "4": {
            "crop_coord": [
                144.80278027777777,
                168.21633250000014,
                830.0250075,
                525.2805413888889
            ],
            "bbox": [
                53.9290009,
                604.6990051,
                297.0090027,
                729.6421203
            ],
            "page": "6"
        },
        "5": {
            "crop_coord": [
                144.80278027777777,
                168.2320572222225,
                1572.052798888889,
                383.73331694444454
            ],
            "bbox": [
                53.9290009,
                655.6560059,
                564.1390076,
                729.6364593999999
            ],
            "page": "7"
        },
        "6": {
            "crop_coord": [
                886.9277613888887,
                168.22311388888886,
                1572.0110913888889,
                418.5527716666667
            ],
            "bbox": [
                321.0939941,
                643.1210022,
                564.1239929,
                729.639679
            ],
            "page": "8"
        },
        "7": {
            "crop_coord": [
                144.80278027777777,
                1336.0147772222222,
                829.8861102777778,
                1586.344435
            ],
            "bbox": [
                53.9290009,
                222.7160034,
                296.9589997,
                309.2346802
            ],
            "page": "9"
        }
    }
}