{
    "captions": {
        "1": {
            "caption": "Figure 1: Photo sharing experience in Facebook Spaces\u00a9 with\nremote partners (a) and (b) looking at the same photo.\n",
            "bbox": [
                317.9556,
                365.59242400000005,
                558.2033464000001,
                386.50824320000004
            ],
            "page": "1"
        },
        "2": {
            "caption": "Figure 2: Methodological approach for constructing our So-\ncialVR questionnaire.\n",
            "bbox": [
                317.9556,
                533.606724,
                559.8063072,
                553.5300648
            ],
            "page": "2"
        },
        "3": {
            "caption": "Figure 3: An example of experience timeline and five phases\nof actions during face-to-face photo sharing.\n",
            "bbox": [
                317.9556,
                595.8419240000001,
                558.2013215999999,
                615.7652648000001
            ],
            "page": "4"
        },
        "4": {
            "caption": "Figure 4: Correspondence analysis, showing three distinct\nexperience components, along with the 20 (numerically dis-\nplayed) interactions.\n",
            "bbox": [
                53.7981,
                455.78268320000006,
                295.6488072,
                486.6629648
            ],
            "page": "6"
        },
        "5": {
            "caption": "Figure 5: Illustrations of the three experimental conditions:\n(a) Face-to-face (b) Skype (c) FB Spaces.\n",
            "bbox": [
                317.6776416,
                492.363624,
                559.3490208,
                512.2869648
            ],
            "page": "7"
        },
        "6": {
            "caption": "Figure 6: (a)-(c) Sum of scores boxplots for across photo sharing conditions for face-to-face (F2F), FB Spaces (FBS), Skype (SKP).\n(d) Self-reported emotion ratings for each condition. ** = p<.001\n",
            "bbox": [
                53.51972320000003,
                527.7272800000001,
                559.7357679999996,
                547.6506208000001
            ],
            "page": "10"
        }
    },
    "crops": {
        "1": {
            "crop_coord": [
                892.8166791666666,
                920.5666944444446,
                1083.5166847222222,
                1014.9333444444444
            ],
            "bbox": [
                323.2140045,
                428.423996,
                388.2660065,
                458.79598999999996
            ],
            "page": "1"
        },
        "2": {
            "crop_coord": [
                1072.9833475,
                920.5666944444446,
                1263.6833530555555,
                1014.9333444444444
            ],
            "bbox": [
                388.0740051,
                428.423996,
                453.12600710000004,
                458.79598999999996
            ],
            "page": "1"
        },
        "3": {
            "crop_coord": [
                1253.3166758333332,
                920.5666944444446,
                1443.8500213888888,
                1014.9333444444444
            ],
            "bbox": [
                452.9940033,
                428.423996,
                517.9860077,
                458.79598999999996
            ],
            "page": "1"
        },
        "4": {
            "crop_coord": [
                1433.4833441666665,
                920.5666519444445,
                1534.0166641666665,
                1098.7666575
            ],
            "bbox": [
                517.8540039,
                398.2440033,
                550.4459991,
                458.7960053
            ],
            "page": "1"
        },
        "5": {
            "crop_coord": [
                892.8166791666666,
                1004.5666672222222,
                1083.5166847222222,
                1098.7666575
            ],
            "bbox": [
                323.2140045,
                398.2440033,
                388.2660065,
                428.5559998
            ],
            "page": "1"
        },
        "6": {
            "crop_coord": [
                1072.9833475,
                1004.5666672222222,
                1263.6833530555555,
                1098.7666575
            ],
            "bbox": [
                388.0740051,
                398.2440033,
                453.12600710000004,
                428.5559998
            ],
            "page": "1"
        },
        "7": {
            "crop_coord": [
                1253.3166758333332,
                1004.5666672222222,
                1443.8500213888888,
                1098.7666575
            ],
            "bbox": [
                452.9940033,
                398.2440033,
                517.9860077,
                428.5559998
            ],
            "page": "1"
        },
        "8": {
            "crop_coord": [
                893.1499988888888,
                252.23334416666688,
                1533.8500044444443,
                458.93333444444465
            ],
            "bbox": [
                323.3339996,
                628.5839996,
                550.3860016,
                699.3959960999999
            ],
            "page": "4"
        },
        "9": {
            "crop_coord": [
                963.1499905555556,
                252.23334416666688,
                1463.6833105555556,
                746.4333344444445
            ],
            "bbox": [
                348.5339966,
                525.0839996,
                525.1259918000001,
                699.3959960999999
            ],
            "page": "7"
        }
    }
}