{
    "captions": {
        "1": {
            "caption": "Figure 1. Standard eye charts in the study: (a) an ETDRS R \nlogMAR chart to measure visual acuity; (b) a Pelli-Robson \nchart to measure contrast sensitivity. \n",
            "bbox": [
                323.1654,
                75.24504,
                554.80908,
                105.00192000000001
            ],
            "page": "4"
        },
        "4": {
            "caption": "Figure 4. The 20-foot walking path labeled with Post-It notes.          \n",
            "bbox": [
                320.2892,
                284.76192000000003,
                577.997456,
                293.64192
            ],
            "page": "5"
        },
        "5": {
            "caption": "Figure 5. A triangle with different colors on black and white \nbackgrounds.  \n",
            "bbox": [
                59.748,
                233.40336,
                292.6100159999999,
                252.60191999999998
            ],
            "page": "6"
        },
        "7": {
            "caption": "Figure 7. Text with different colors on black and white \nbackgrounds. We use \u201cTurn Left\u201d as an example. \n",
            "bbox": [
                333.1757800000001,
                634.44312,
                544.8021640000001,
                653.88144
            ],
            "page": "6"
        },
        "8": {
            "caption": "Figure 8. Text on black and white backgrounds with (a) \ndifferent fonts: Verdana and Times New Roman, and (b) \ndifferent thickness levels: Regular and Bold. \n",
            "bbox": [
                329.04699999999997,
                531.7250399999999,
                549.0654199999999,
                561.48552
            ],
            "page": "6"
        },
        "6": {
            "caption": "Figure 6. A triangle on black and white backgrounds with \ndifferent thickness levels: Thin, Medium, and Thick \n",
            "bbox": [
                64.0992,
                145.56359999999998,
                288.34598800000003,
                165.00191999999998
            ],
            "page": "6"
        }
    },
    "crops": {
        "1": {
            "crop_coord": [
                146.44445638888888,
                1752.4999066666667,
                822.444441111111,
                2067.1665530555556
            ],
            "bbox": [
                54.5200043,
                49.6200409,
                294.2799988,
                159.3000336
            ],
            "page": "1"
        },
        "2": {
            "crop_coord": [
                876.4447191666667,
                1602.7502780555553,
                1551.7224969444442,
                1898.8613891666666
            ],
            "bbox": [
                317.3200989,
                110.2098999,
                556.8200989,
                213.20989989999998
            ],
            "page": "4"
        },
        "3": {
            "crop_coord": [
                876.4444647222222,
                1831.9999777777778,
                986.4444647222222,
                1871.9999863888888
            ],
            "bbox": [
                317.3200073,
                119.8800049,
                353.3200073,
                130.68000800000002
            ],
            "page": "4"
        },
        "4": {
            "crop_coord": [
                1222.4444580555555,
                1837.9999880555554,
                1332.4444580555555,
                1877.9999966666667
            ],
            "bbox": [
                441.8800049,
                117.7200012,
                477.8800049,
                128.5200043
            ],
            "page": "4"
        },
        "5": {
            "crop_coord": [
                129.1111077777778,
                127.33333138888881,
                1573.7777625,
                1267.3333400000001
            ],
            "bbox": [
                48.2799988,
                337.5599976,
                564.7599945000001,
                744.3600007
            ],
            "page": "4"
        },
        "6": {
            "crop_coord": [
                876.4447191666667,
                1172.8040991666664,
                1560.671946388889,
                1453.0200025
            ],
            "bbox": [
                317.3200989,
                270.7127991,
                560.0419007,
                367.9905243
            ],
            "page": "5"
        },
        "7": {
            "crop_coord": [
                167.27778972222222,
                166.66642083333338,
                794.7777983333334,
                423.6766730555556
            ],
            "bbox": [
                62.0200043,
                641.2763977,
                284.3200074,
                730.2000885
            ],
            "page": "5"
        },
        "8": {
            "crop_coord": [
                987.5558302777778,
                854.1094547222223,
                1431.7225055555555,
                1158.1369527777777
            ],
            "bbox": [
                357.3200989,
                376.870697,
                513.620102,
                482.7205963
            ],
            "page": "5"
        },
        "9": {
            "crop_coord": [
                993.1111313888888,
                1109.3330469444445,
                1096.4444816666667,
                1147.999733888889
            ],
            "bbox": [
                359.3200073,
                380.5200958,
                392.9200134,
                390.84010309999996
            ],
            "page": "5"
        },
        "10": {
            "crop_coord": [
                1198.444459722222,
                1109.3330469444445,
                1302.4444494444444,
                1147.999733888889
            ],
            "bbox": [
                433.2400055,
                380.5200958,
                467.0800018,
                390.84010309999996
            ],
            "page": "5"
        },
        "11": {
            "crop_coord": [
                181.1666786111111,
                1302.6853011111111,
                785.6111230555555,
                1491.0186258333335
            ],
            "bbox": [
                67.0200043,
                257.0332947,
                281.0200043,
                321.23329160000003
            ],
            "page": "6"
        },
        "12": {
            "crop_coord": [
                313.11112305555554,
                1563.5136158333335,
                650.697233611111,
                1731.8469491666665
            ],
            "bbox": [
                114.5200043,
                170.3350983,
                232.45100409999998,
                227.3350983
            ],
            "page": "6"
        },
        "13": {
            "crop_coord": [
                876.4447191666667,
                166.66637833333334,
                1553.111385833333,
                376.6663783333334
            ],
            "bbox": [
                317.3200989,
                658.2001038,
                557.3200989,
                730.2001038
            ],
            "page": "6"
        },
        "14": {
            "crop_coord": [
                1225.6244319444445,
                449.1617075,
                1494.5001727777778,
                630.9858449999998
            ],
            "bbox": [
                443.0247955,
                566.6450958,
                536.2200622,
                628.5017853
            ],
            "page": "6"
        },
        "15": {
            "crop_coord": [
                952.8333536111111,
                449.16158055555536,
                1220.7445694444446,
                631.9502852777777
            ],
            "bbox": [
                344.8200073,
                566.2978973,
                437.668045,
                628.501831
            ],
            "page": "6"
        },
        "16": {
            "crop_coord": [
                953.1111061111111,
                584.0000236111111,
                1061.7777847222221,
                623.3333502777778
            ],
            "bbox": [
                344.9199982,
                569.3999939,
                380.4400025,
                579.9599915
            ],
            "page": "6"
        },
        "17": {
            "crop_coord": [
                1225.7777827777777,
                584.0000236111111,
                1335.1111008333332,
                623.3333502777778
            ],
            "bbox": [
                443.0800018,
                569.3999939,
                478.8399963,
                579.9599915
            ],
            "page": "6"
        },
        "18": {
            "crop_coord": [
                129.1111077777778,
                1805.2776844444443,
                1571.7777591666666,
                2044.611011111111
            ],
            "bbox": [
                48.2799988,
                57.740036,
                564.0399933,
                140.3000336
            ],
            "page": "6"
        },
        "19": {
            "crop_coord": [
                103.97221027777778,
                1627.4999066666667,
                1583.9722016666667,
                2092.1665530555556
            ],
            "bbox": [
                39.2299957,
                40.6200409,
                568.4299926,
                204.3000336
            ],
            "page": "7"
        },
        "20": {
            "crop_coord": [
                104.77778972222222,
                1618.9998711111114,
                1599.4444444444443,
                2058.999879722222
            ],
            "bbox": [
                39.5200043,
                52.5600433,
                574.0,
                207.3600464
            ],
            "page": "8"
        }
    }
}